first_breaks/VERSION
first_breaks/__init__.py
first_breaks/__main__.py
first_breaks/cli.py
first_breaks/const.py
first_breaks/data_models/__init__.py
first_breaks/data_models/dependent.py
first_breaks/data_models/independent.py
first_breaks/data_models/initialised_defaults.py
first_breaks/desktop/__init__.py
first_breaks/desktop/bandfilter_widget.py
first_breaks/desktop/byte_encode_unit_widget.py
first_breaks/desktop/combobox_with_mapping.py
first_breaks/desktop/export_widgets.py
first_breaks/desktop/graph.py
first_breaks/desktop/last_folder_manager.py
first_breaks/desktop/main_gui.py
first_breaks/desktop/multiselect_widget.py
first_breaks/desktop/nn_manager.py
first_breaks/desktop/picks_manager_widget.py
first_breaks/desktop/radioset_widget.py
first_breaks/desktop/roi_manager.py
first_breaks/desktop/settings_processing_widget.py
first_breaks/desktop/slider_with_values.py
first_breaks/desktop/spectrum_window.py
first_breaks/desktop/threads.py
first_breaks/desktop/tooltip_widget.py
first_breaks/desktop/utils.py
first_breaks/exports/__init__.py
first_breaks/exports/export_picks.py
first_breaks/picking/__init__.py
first_breaks/picking/ipicker.py
first_breaks/picking/picker_onnx.py
first_breaks/picking/picks.py
first_breaks/picking/refiner.py
first_breaks/picking/task.py
first_breaks/picking/utils.py
first_breaks/sgy/__init__.py
first_breaks/sgy/headers.py
first_breaks/sgy/reader.py
first_breaks/utils/__init__.py
first_breaks/utils/cuda.py
first_breaks/utils/debug.py
first_breaks/utils/filtering.py
first_breaks/utils/fourier_transforms.py
first_breaks/utils/utils.py
first_breaks_picking_gpu-0.7.9.dist-info/licenses/LICENSE
first_breaks_picking_gpu-0.7.9.dist-info/METADATA
first_breaks_picking_gpu-0.7.9.dist-info/WHEEL
first_breaks_picking_gpu-0.7.9.dist-info/entry_points.txt
first_breaks_picking_gpu-0.7.9.dist-info/top_level.txt
first_breaks_picking_gpu-0.7.9.dist-info/RECORD
